{
  "fe-avatar": {
    "attributes": [
      "stacked",
      "isSquare",
      "size",
      "text",
      "src",
      "className"
    ]
  },
  "fe-avatarGroup": {
    "attributes": [
      "count"
    ]
  },
  "fe-badge": {
    "attributes": [
      "size",
      "type",
      "dot"
    ]
  },
  "fe-badgeAnchor": {
    "attributes": [
      "placement"
    ]
  },
  "fe-breadcrumbs": {
    "attributes": [
      "size",
      "separator"
    ]
  },
  "fe-breadcrumbsItem": {
    "attributes": [
      "herf",
      "to"
    ]
  },
  "fe-button": {
    "attributes": [
      "type",
      "size",
      "auto",
      "disabled",
      "shadow",
      "loading"
    ]
  },
  "fe-capacity": {
    "attributes": [
      "value",
      "color"
    ]
  },
  "fe-card": {
    "attributes": [
      "hoverable",
      "shadow"
    ]
  },
  "fe-checkbox": {
    "attributes": [
      "v-model",
      "size",
      "disabled",
      "label"
    ]
  },
  "fe-checkboxGroup": {
    "attributes": [
      "v-model",
      "size",
      "disabled",
      "useRow"
    ]
  },
  "fe-code": {
    "attributes": [
      "block"
    ]
  },
  "fe-dot": {
    "attributes": [
      "type"
    ]
  },
  "fe-image": {
    "attributes": [
      "src",
      "width",
      "height",
      "skeleton",
      "maxDelay",
      "useBrowser",
      "title",
      "url",
      "showFullLink",
      "invert"
    ]
  },
  "fe-input": {
    "attributes": [
      "v-model",
      "prefix",
      "suffix",
      "clearable"
    ]
  },
  "fe-row": {
    "attributes": [
      "tag",
      "gutter",
      "justify",
      "align"
    ]
  },
  "fe-col": {
    "attributes": [
      "tag",
      "span",
      "offset"
    ]
  },
  "fe-link": {
    "attributes": [
      "href",
      "to",
      "color",
      "underline",
      "block"
    ]
  },
  "fe-loading": {
    "attributes": [
      "size",
      "type",
      "color"
    ]
  },
  "fe-modal": {
    "attributes": [
      "v-model:visible",
      "title",
      "width",
      "cancel",
      "done"
    ]
  },
  "fe-pagination": {
    "attributes": [
      "v-model",
      "count",
      "size",
      "limit",
      "simple",
      "prevText",
      "nextText"
    ]
  },
  "fe-radio": {
    "attributes": [
      "checked",
      "disabed",
      "value",
      "size"
    ]
  },
  "fe-radioGroup": {
    "attributes": [
      "initialValue",
      "useRow",
      "disabed",
      "size"
    ]
  },
  "fe-select": {
    "attributes": [
      "v-model",
      "placeholder",
      "multiple",
      "size",
      "width",
      "clearable",
      "disabled"
    ]
  },
  "fe-option": {
    "attributes": [
      "value",
      "label",
      "disabed"
    ]
  },
  "fe-snippet": {
    "attributes": [
      "text",
      "type",
      "fill",
      "width",
      "copy",
      "symbol",
      "toastText",
      "toastType"
    ]
  },
  "fe-spacer": {
    "attributes": [
      "x",
      "y",
      "inline"
    ]
  },
  "fe-switch": {
    "attributes": [
      "checked",
      "size",
      "disabed"
    ]
  },
  "fe-tabs": {
    "attributes": [
      "v-model:active",
      "hideDivider"
    ]
  },
  "fe-tab": {
    "attributes": [
      "title",
      "value"
    ]
  },
  "fe-tag": {
    "attributes": [
      "text",
      "type",
      "useInvert"
    ]
  },
  "fe-toast": {
    "attributes": [
      "text",
      "type",
      "duration"
    ]
  },
  "fe-progress": {
    "attributes": [
      "value",
      "max",
      "type",
      "colors"
    ]
  }
}